[1,["fenS3S3W9FGpcO6HuOtlWr","ebUD7e6YRNori1Ehd+1kiF@f9941","20g1ukYUVPvKWKBRznAKo+@f9941","54TknWPwVPqJqeCR+Y/Czo@f9941","95EkngnxZFbYuFpsqVTaFr@f9941","f1KiPEuSRDIqJgPZgkKPHo@f9941","90sna/9URPraJG2aDRk00T@f9941","98NRVuuEZGc5d0NV2cO+ek@f9941","c58HxGblZJRIzEoDCVkChZ@f9941","f8lxRGzcpFfY8jXiA8OBw5@f9941","20g1ukYUVPvKWKBRznAKo+@6c48a","54TknWPwVPqJqeCR+Y/Czo@6c48a","90sna/9URPraJG2aDRk00T@6c48a","95EkngnxZFbYuFpsqVTaFr@6c48a","98NRVuuEZGc5d0NV2cO+ek@6c48a","c58HxGblZJRIzEoDCVkChZ@6c48a","76IZ9imjlDZJyR9/xwgsoj","d0j/Y9uuBPu6jDFnlmUIv5","c5dPW2UF5H2b3O3O03r01B","ebUD7e6YRNori1Ehd+1kiF@6c48a","f1KiPEuSRDIqJgPZgkKPHo@6c48a","f8lxRGzcpFfY8jXiA8OBw5@6c48a"],["node","_textureSource","_parent","_spriteFrame","root","asset","_target","_normalSprite","_hoverSprite","_pressedSprite","_disabledSprite","_clip","scoreText","toggleSoundBtn","soundMute","soundPlay","replayBtn","playBtn","canvas","gameOverSound","hitSound","shootSound","scene","data"],[["cc.Node",["_name","_layer","_id","_components","_parent","_children","_lpos","_prefab"],0,9,1,2,5,4],"cc.SpriteFrame",["cc.Sprite",["_sizeMode","_type","node","_spriteFrame","_color","__prefab"],1,1,6,5,4],["cc.Node",["_name","_layer","_id","_objFlags","__editorExtras__","_components","_lpos","_parent","_children","_prefab"],-2,12,5,1,2,4],["cc.UITransform",["node","_contentSize","__prefab"],3,1,5,4],["cc.Node",["_name","_parent","_components","_lpos"],2,1,2,5],["cc.RigidBody2D",["enabledContactListener","_type","node","__prefab"],1,1,4],["cc.CircleCollider2D",["_radius","node","_offset","__prefab"],2,1,5,4],["cc.Label",["_string","_actualFontSize","_fontSize","_lineHeight","node","_color"],-1,1,5],["cc.AudioClip",["_name","_native","_duration"],0],["cc.SceneAsset",["_name"],2],["cc.Widget",["_alignFlags","_top","_bottom","node"],0,1],["35b938WFQdEVaDFT6B9a/Wl",["node"],3,1],["cc.Layout",["node"],3,1],["8360cZ2YTlMXaEzYUK4dQcL",["node","toggleSoundBtn","scoreText","replayBtn","soundMute","soundPlay"],3,1,1,1,1,6,6],["cc.BlockInputEvents",["node"],3,1],["be77fJgH7VKo7TW/x6OxYY+",["node","toggleSoundBtn","playBtn","soundMute","soundPlay"],3,1,1,1,6,6],["fc84dBz6l5C0Kar6It/Y/A9",["speedRotation","speedShoot","node","canvas"],1,1,1],["8f328VdlgZIx6JR0ABZTwnd",["node","scoreText"],3,1,1],["cc.Button",["_transition","node","_normalColor","_target","_normalSprite","_hoverSprite","_pressedSprite","_disabledSprite"],2,1,5,1,6,6,6,6],["bc2cd3UVQZGhaHX1gcAX6ls",["node"],3,1],["cc.BoxCollider2D",["node","_size"],3,1,5],["dc636ANRRJN66V4xggc9Mre",["node","shootSound","hitSound","gameOverSound"],3,1,1,1,1],["cc.Scene",["_name","_children","_prefab","_globals"],2,2,4,4],["cc.PrefabInfo",["root","asset","fileId","instance","targetOverrides","nestedPrefabInstanceRoots"],-2,2],["cc.PrefabInfo",["fileId","targetOverrides","nestedPrefabInstanceRoots","root","instance","asset"],0,1,4,6],["cc.PrefabInfo",["fileId","instance","targetOverrides","nestedPrefabInstanceRoots","root","asset"],-1,1,1],["cc.SceneGlobals",["ambient","shadows","_skybox","fog","octree","skin","lightProbeInfo","postSettings"],3,4,4,4,4,4,4,4,4],["cc.AmbientInfo",["_skyColorHDR","_groundAlbedoHDR"],3,5,5],["cc.ShadowsInfo",["_shadowColor","_size"],3,5,5],["cc.SkyboxInfo",[],3],["cc.FogInfo",[],3],["cc.OctreeInfo",[],3],["cc.SkinInfo",["_enabled"],2],["cc.LightProbeInfo",[],3],["cc.PostSettingsInfo",[],3],["cc.TargetInfo",["localID"],2],["cc.PrefabInstance",["fileId","prefabRootNode","propertyOverrides"],1,9],["CCPropertyOverrideInfo",["value","propertyPath","targetInfo"],1,1],["CCPropertyOverrideInfo",["propertyPath","targetInfo","value"],2,1,8],["CCPropertyOverrideInfo",["propertyPath","targetInfo","value"],2,4,8],["cc.Camera",["_projection","_orthoHeight","_near","_visibility","node","_color"],-1,1,5],["cc.Canvas",["node","_cameraComponent"],3,1,1],["242cbcMc8NGoLa6fplutuOt",["node"],3,1],["cc.AudioSource",["_playOnAwake","node"],2,1],["cc.Prefab",["_name"],2],["cc.CompPrefabInfo",["fileId"],2],["4cff9mVN4pIvardTHImZ4vO",["node","__prefab"],3,1,4]],[[39,0,1,2,2],[4,0,1,1],[36,0,2],[3,3,4,7,9,3],[4,0,1],[25,0,1,2,3,4,5,4],[37,0,1,2,3],[38,0,1,2,3],[46,0,2],[0,0,1,4,3,6,3],[6,0,1,2,3],[0,0,1,4,5,3,3],[0,0,1,3,6,3],[2,1,0,2,3,3],[19,0,1,2,3,4,5,6,7,2],[20,0,1],[21,0,1,1],[9,0,1,2,4],[5,0,1,2,2],[13,0,1],[40,0,1,2,2],[44,0,1,2],[3,0,1,7,5,6,3],[0,0,1,5,3,3],[0,0,1,4,5,3,6,3],[0,0,1,4,3,3],[4,0,2,1,1],[15,0,1],[2,1,0,2,4,3,3],[26,0,1,2,3,4,5,5],[10,0,2],[3,0,1,2,8,5,6,4],[0,0,4,5,3,2],[0,0,2,5,3,3],[0,0,2,4,3,3],[0,0,5,3,7,2],[0,0,4,3,7,2],[5,0,1,2,3,2],[11,0,1,2,3,4],[12,0,1],[14,0,1,2,3,4,5,1],[16,0,1,2,3,4,1],[17,0,1,2,3,3],[6,0,1,2,3,3],[7,0,1,2,2],[7,0,1,3,2],[18,0,1,1],[2,0,2,3,2],[2,0,2,5,3,2],[22,0,1,2,3,1],[23,0,1,2,3,2],[24,0,1,2,3,4,5,6],[27,0,1,2,3,4,5,6,7,1],[28,0,1,1],[29,0,1,1],[30,1],[31,1],[32,1],[33,0,2],[34,1],[35,1],[41,0,1,2,3,4,5,5],[42,0,1,1],[8,0,1,2,3,4,5],[8,0,1,2,3,4,5,5],[43,0,1],[45,0,2],[47,0,1,1]],[[[{"name":"default_btn_normal","rect":{"x":0,"y":0,"width":40,"height":40},"offset":{"x":0,"y":0},"originalSize":{"width":40,"height":40},"rotated":false,"capInsets":[12,12,12,12],"vertices":{"rawPosition":[-20,-20,0,20,-20,0,-20,20,0,20,20,0],"indexes":[0,1,2,2,1,3],"uv":[0,40,40,40,0,0,40,0],"nuv":[0,0,1,0,0,1,1,1],"minPos":{"x":-20,"y":-20,"z":0},"maxPos":{"x":20,"y":20,"z":0}},"packable":true,"pixelsToUnit":100,"pivot":{"x":0.5,"y":0.5},"meshType":0}],[1],0,[0],[1],[10]],[[{"name":"default_btn_pressed","rect":{"x":0,"y":0,"width":40,"height":40},"offset":{"x":0,"y":0},"originalSize":{"width":40,"height":40},"rotated":false,"capInsets":[12,12,12,12],"vertices":{"rawPosition":[-20,-20,0,20,-20,0,-20,20,0,20,20,0],"indexes":[0,1,2,2,1,3],"uv":[0,40,40,40,0,0,40,0],"nuv":[0,0,1,0,0,1,1,1],"minPos":{"x":-20,"y":-20,"z":0},"maxPos":{"x":20,"y":20,"z":0}},"packable":true,"pixelsToUnit":100,"pivot":{"x":0.5,"y":0.5},"meshType":0}],[1],0,[0],[1],[11]],[[[17,"shoot",".mp3",1.008],-1],0,0,[],[],[]],[[{"name":"default_panel","rect":{"x":0,"y":0,"width":20,"height":20},"offset":{"x":0,"y":0},"originalSize":{"width":20,"height":20},"rotated":false,"capInsets":[4,4,4,4],"vertices":{"rawPosition":[-10,-10,0,10,-10,0,-10,10,0,10,10,0],"indexes":[0,1,2,2,1,3],"uv":[0,20,20,20,0,0,20,0],"nuv":[0,0,1,0,0,1,1,1],"minPos":{"x":-10,"y":-10,"z":0},"maxPos":{"x":10,"y":10,"z":0}},"packable":true,"pixelsToUnit":100,"pivot":{"x":0.5,"y":0.5},"meshType":0}],[1],0,[0],[1],[12]],[[{"name":"default_btn_disabled","rect":{"x":0,"y":0,"width":40,"height":40},"offset":{"x":0,"y":0},"originalSize":{"width":40,"height":40},"rotated":false,"capInsets":[12,12,12,12],"vertices":{"rawPosition":[-20,-20,0,20,-20,0,-20,20,0,20,20,0],"indexes":[0,1,2,2,1,3],"uv":[0,40,40,40,0,0,40,0],"nuv":[0,0,1,0,0,1,1,1],"minPos":{"x":-20,"y":-20,"z":0},"maxPos":{"x":20,"y":20,"z":0}},"packable":true,"pixelsToUnit":100,"pivot":{"x":0.5,"y":0.5},"meshType":0}],[1],0,[0],[1],[13]],[[{"name":"PictoIcon_Refresh_1","rect":{"x":73,"y":48,"width":365,"height":416},"offset":{"x":-0.5,"y":0},"originalSize":{"width":512,"height":512},"rotated":false,"capInsets":[0,0,0,0],"vertices":{"rawPosition":[-182.5,-208,0,182.5,-208,0,-182.5,208,0,182.5,208,0],"indexes":[0,1,2,2,1,3],"uv":[73,464,438,464,73,48,438,48],"nuv":[0.142578125,0.09375,0.85546875,0.09375,0.142578125,0.90625,0.85546875,0.90625],"minPos":{"x":-182.5,"y":-208,"z":0},"maxPos":{"x":182.5,"y":208,"z":0}},"packable":true,"pixelsToUnit":100,"pivot":{"x":0.5,"y":0.5},"meshType":0}],[1],0,[0],[1],[14]],[[[17,"game-over",".mp3",2.037531],-1],0,0,[],[],[]],[[{"name":"PictoIcon_Sound_Off","rect":{"x":37,"y":49,"width":438,"height":416},"offset":{"x":0,"y":-1},"originalSize":{"width":512,"height":512},"rotated":false,"capInsets":[0,0,0,0],"vertices":{"rawPosition":[-219,-208,0,219,-208,0,-219,208,0,219,208,0],"indexes":[0,1,2,2,1,3],"uv":[37,463,475,463,37,47,475,47],"nuv":[0.072265625,0.091796875,0.927734375,0.091796875,0.072265625,0.904296875,0.927734375,0.904296875],"minPos":{"x":-219,"y":-208,"z":0},"maxPos":{"x":219,"y":208,"z":0}},"packable":true,"pixelsToUnit":100,"pivot":{"x":0.5,"y":0.5},"meshType":0}],[1],0,[0],[1],[15]],[[[17,"hit",".mp3",1.008],-1],0,0,[],[],[]],[[[30,"scene"],[31,"Canvas",33554432,"beI88Z2HpFELqR4T5EMHpg",[-4,-5,-6,-7,-8],[[[1,-1,[5,1080,1920]],-2,[38,45,5.684341886080802e-14,5.684341886080802e-14,-3]],4,1,4],[1,540,960,0]],[32,"GameManager",1,[-10,-11,-12,-13,-14,-15],[[39,-9]]],[23,"GameOverScreen",33554432,[-23,-24,-25],[[4,-16],[19,-17],[40,-21,-20,-19,-18,18,19],[27,-22]]],[23,"HomeScreen",33554432,[-32,-33],[[4,-26],[19,-27],[41,-30,-29,-28,31,32],[27,-31]]],[11,"Projectile",33554432,1,[-39],[[1,-34,[5,31,31]],[42,5,2,-36,-35],[10,true,1,-37],[44,30,-38,[0,120,0]]]],[11,"UIManager",33554432,1,[-43,3,4],[[4,-40],[46,-42,-41]]],[12,"ReplayBtn",33554432,[[1,-44,[5,80,80]],[13,1,0,-45,8],[14,3,-47,[4,4292269782],-46,9,10,11,12]],[1,-80,0,0]],[12,"SoundBtn",33554432,[[1,-48,[5,80,80]],[13,1,0,-49,13],[14,3,-51,[4,4292269782],-50,14,15,16,17]],[1,80,0,0]],[12,"PlayBtn",33554432,[[1,-52,[5,80,80]],[13,1,0,-53,21],[14,3,-55,[4,4292269782],-54,22,23,24,25]],[1,-80,0,0]],[12,"SoundBtn",33554432,[[1,-56,[5,80,80]],[13,1,0,-57,26],[14,3,-59,[4,4292269782],-58,27,28,29,30]],[1,80,0,0]],[11,"Obstacles",33554432,1,[-61,-62,-63,-64],[[4,-60]]],[9,"Obstacle",33554432,11,[[1,-65,[5,20,1920]],[15,-66],[16,-67,[5,20,1920]],[10,true,0,-68]],[1,-540,0,0]],[9,"Obstacle-001",33554432,11,[[1,-69,[5,20,1920]],[15,-70],[16,-71,[5,20,1920]],[10,true,0,-72]],[1,540,0,0]],[9,"Obstacle-002",33554432,11,[[1,-73,[5,1080,20]],[15,-74],[16,-75,[5,1080,20]],[10,true,0,-76]],[1,0,-960,0]],[9,"Obstacle-003",33554432,11,[[1,-77,[5,1080,20]],[15,-78],[16,-79,[5,1080,20]],[10,true,0,-80]],[1,0,960,0]],[33,"SoundManager","32ftOk2JhHqZ0nKOeyrmdV",[-85,-86,-87],[[49,-84,-83,-82,-81]]],[50,"scene",[1,-94,16],[51,null,null,"dd6dba8f-02d7-44f2-a220-5ec0dd160458",null,null,[-88,-89,-90,-91,-92,-93]],[52,[53,[2,0,0,0,0.520833125],[2,0,0,0,0]],[54,[4,4283190348],[0,512,512]],[55],[56],[57],[58,false],[59],[60]]],[2,["281bdwUuNHvI3khn9TYqcW"]],[2,["281bdwUuNHvI3khn9TYqcW"]],[2,["281bdwUuNHvI3khn9TYqcW"]],[2,["281bdwUuNHvI3khn9TYqcW"]],[2,["281bdwUuNHvI3khn9TYqcW"]],[2,["281bdwUuNHvI3khn9TYqcW"]],[11,"PlayScreen",33554432,6,[-97],[[4,-95],[19,-96]]],[24,"Actions",33554432,3,[7,8],[[4,-98]],[1,0,-200,0]],[24,"Actions",33554432,4,[9,10],[[1,-99,[5,220,100]]],[1,0,-200,0]],[3,0,{},2,[5,"281bdwUuNHvI3khn9TYqcW",null,null,-100,[6,"2aSviT2gtAr67Dl8sh5YKg",null,[[7,"Bubble",["_name"],18],[0,["_lpos"],18,[1,350,0,0]],[0,["_lrot"],18,[3,0,0,0,1]],[0,["_euler"],18,[1,0,0,0]]]],0]],[3,0,{},2,[5,"281bdwUuNHvI3khn9TYqcW",null,null,-101,[6,"ef2l5moMxLvb90fCPtbDZu",null,[[7,"Bubble-001",["_name"],19],[0,["_lpos"],19,[1,180,300,0]],[0,["_lrot"],19,[3,0,0,0,1]],[0,["_euler"],19,[1,0,0,0]],[20,["_offset"],[2,["69+WwyDupIe6BQCsstujRs"]],[0,0,0]]]],1]],[3,0,{},2,[5,"281bdwUuNHvI3khn9TYqcW",null,null,-102,[6,"47f+Ws+e5Lm5ijioobrtEI",null,[[7,"Bubble-002",["_name"],20],[0,["_lpos"],20,[1,-180,300,0]],[0,["_lrot"],20,[3,0,0,0,1]],[0,["_euler"],20,[1,0,0,0]],[20,["_offset"],[2,["69+WwyDupIe6BQCsstujRs"]],[0,0,0]]]],2]],[3,0,{},2,[5,"281bdwUuNHvI3khn9TYqcW",null,null,-103,[6,"8dh27Fya9E0be9V/g0jSKA",null,[[7,"Bubble-003",["_name"],21],[0,["_lpos"],21,[1,-350,0,0]],[0,["_lrot"],21,[3,0,0,0,1]],[0,["_euler"],21,[1,0,0,0]],[20,["_offset"],[2,["69+WwyDupIe6BQCsstujRs"]],[0,0,0]]]],3]],[3,0,{},2,[5,"281bdwUuNHvI3khn9TYqcW",null,null,-104,[6,"7fuDr/S+pOd7RhDeEcmnKx",null,[[7,"Bubble-004",["_name"],22],[0,["_lpos"],22,[1,-180,-300,0]],[0,["_lrot"],22,[3,0,0,0,1]],[0,["_euler"],22,[1,0,0,0]]]],4]],[3,0,{},2,[5,"281bdwUuNHvI3khn9TYqcW",null,null,-105,[6,"dfYJ92tWlCT4rngJ7dCuOA",null,[[7,"Bubble-005",["_name"],23],[0,["_lpos"],23,[1,180,-300,0]],[0,["_lrot"],23,[3,0,0,0,1]],[0,["_euler"],23,[1,0,0,0]]]],5]],[9,"Avatar",33554432,5,[[1,-106,[5,60,60]],[47,0,-107,6]],[1,120,0,0]],[22,"ScoreText",33554432,24,[[[1,-108,[5,111.23046875,252]],-109],4,1],[1,0,700,0]],[25,"BG",33554432,3,[[1,-110,[5,1080,2500]],[28,1,0,-111,[4,4294740038],7]]],[22,"Score",33554432,3,[[[1,-112,[5,207.6171875,252]],-113],4,1],[1,0,200,0]],[25,"BG",33554432,4,[[1,-114,[5,1080,2500]],[28,1,0,-115,[4,4294740038],20]]],[37,"Camera",1,[-116],[1,0,0,1000]],[61,0,960,0,1108344832,38,[4,1157400646]],[62,1,39],[63,"1",200,200,200,34],[64,"11",200,200,200,36,[4,4278190080]],[34,"PlayerController","0825iBNdRF/pYxPyr70/E7",17,[[65,-117]]],[18,"ShootSound",16,[-118]],[21,false,44],[18,"HitSound",16,[-119]],[21,false,46],[18,"GameOver",16,[-120]],[21,false,48]],0,[0,0,1,0,-2,40,0,0,1,0,-1,38,0,-2,2,0,-3,5,0,-4,6,0,-5,11,0,0,2,0,-1,27,0,-2,28,0,-3,29,0,-4,30,0,-5,31,0,-6,32,0,0,3,0,0,3,0,16,7,0,12,42,0,13,8,0,0,3,0,0,3,0,-1,35,0,-2,36,0,-3,25,0,0,4,0,0,4,0,17,9,0,13,10,0,0,4,0,0,4,0,-1,37,0,-2,26,0,0,5,0,18,40,0,0,5,0,0,5,0,0,5,0,-1,33,0,0,6,0,12,41,0,0,6,0,-1,24,0,0,7,0,0,7,0,6,7,0,0,7,0,0,8,0,0,8,0,6,8,0,0,8,0,0,9,0,0,9,0,6,9,0,0,9,0,0,10,0,0,10,0,6,10,0,0,10,0,0,11,0,-1,12,0,-2,13,0,-3,14,0,-4,15,0,0,12,0,0,12,0,0,12,0,0,12,0,0,13,0,0,13,0,0,13,0,0,13,0,0,14,0,0,14,0,0,14,0,0,14,0,0,15,0,0,15,0,0,15,0,0,15,0,19,49,0,20,47,0,21,45,0,0,16,0,-1,44,0,-2,46,0,-3,48,0,-1,27,0,-2,28,0,-3,29,0,-4,30,0,-5,31,0,-6,32,0,-2,43,0,0,24,0,0,24,0,-1,34,0,0,25,0,0,26,0,4,27,0,4,28,0,4,29,0,4,30,0,4,31,0,4,32,0,0,33,0,0,33,0,0,34,0,-2,41,0,0,35,0,0,35,0,0,36,0,-2,42,0,0,37,0,0,37,0,-1,39,0,0,43,0,-1,45,0,-1,47,0,-1,49,0,22,17,1,2,17,3,2,6,4,2,6,7,2,25,8,2,25,9,2,26,10,2,26,16,2,17,120],[0,0,0,0,0,0,0,0,0,0,0,0,0,0,0,0,0,0,0,0,0,0,0,0,0,0,0,0,0,0,0,0,0,45,47,49],[5,5,5,5,5,5,3,3,3,7,8,9,10,3,7,8,9,10,14,15,3,3,7,8,9,10,3,7,8,9,10,14,15,11,11,11],[0,0,0,0,0,0,5,6,7,7,2,3,4,1,1,2,3,4,8,1,6,9,9,2,3,4,1,1,2,3,4,8,1,16,17,18]],[[{"name":"PictoIcon_Sound","rect":{"x":35,"y":49,"width":441,"height":416},"offset":{"x":-0.5,"y":-1},"originalSize":{"width":512,"height":512},"rotated":false,"capInsets":[0,0,0,0],"vertices":{"rawPosition":[-220.5,-208,0,220.5,-208,0,-220.5,208,0,220.5,208,0],"indexes":[0,1,2,2,1,3],"uv":[35,463,476,463,35,47,476,47],"nuv":[0.068359375,0.091796875,0.9296875,0.091796875,0.068359375,0.904296875,0.9296875,0.904296875],"minPos":{"x":-220.5,"y":-208,"z":0},"maxPos":{"x":220.5,"y":208,"z":0}},"packable":true,"pixelsToUnit":100,"pivot":{"x":0.5,"y":0.5},"meshType":0}],[1],0,[0],[1],[19]],[[{"name":"default_radio_button_off","rect":{"x":3,"y":3,"width":26,"height":26},"offset":{"x":0,"y":0},"originalSize":{"width":32,"height":32},"rotated":false,"capInsets":[13,13,13,13],"vertices":{"rawPosition":[-13,-13,0,13,-13,0,-13,13,0,13,13,0],"indexes":[0,1,2,2,1,3],"uv":[3,29,29,29,3,3,29,3],"nuv":[0.09375,0.09375,0.90625,0.09375,0.09375,0.90625,0.90625,0.90625],"minPos":{"x":-13,"y":-13,"z":0},"maxPos":{"x":13,"y":13,"z":0}},"packable":true,"pixelsToUnit":100,"pivot":{"x":0.5,"y":0.5},"meshType":0}],[1],0,[0],[1],[20]],[[{"name":"PictoIcon_Play_1","rect":{"x":120,"y":58,"width":290,"height":396},"offset":{"x":9,"y":0},"originalSize":{"width":512,"height":512},"rotated":false,"capInsets":[0,0,0,0],"vertices":{"rawPosition":[-145,-198,0,145,-198,0,-145,198,0,145,198,0],"indexes":[0,1,2,2,1,3],"uv":[120,454,410,454,120,58,410,58],"nuv":[0.234375,0.11328125,0.80078125,0.11328125,0.234375,0.88671875,0.80078125,0.88671875],"minPos":{"x":-145,"y":-198,"z":0},"maxPos":{"x":145,"y":198,"z":0}},"packable":true,"pixelsToUnit":100,"pivot":{"x":0.5,"y":0.5},"meshType":0}],[1],0,[0],[1],[21]],[[[66,"Bubble"],[35,"Bubble",[-6],[[26,-2,[8,"31C6DZGQtN9ZEACBXvRuk1"],[5,50,50]],[67,-3,[8,"79Z85dYudKKot4kJQ5Db3T"]],[43,true,1,-4,[8,"e7FOlXmLFMYIj/rEZ2nkQU"]],[45,60,-5,[8,"69+WwyDupIe6BQCsstujRs"]]],[29,"281bdwUuNHvI3khn9TYqcW",null,null,null,-1,0]],[36,"Avatar",1,[[26,-7,[8,"eck95G381KR5MwNZ5H5auO"],[5,120,120]],[48,0,-8,[8,"d1wPZqcd5POqQrl9m1/Apl"],0]],[29,"6aIB4qDNtN9qm8dgeRF9wM",null,null,null,1,0]]],0,[0,4,1,0,0,1,0,0,1,0,0,1,0,0,1,0,-1,2,0,0,2,0,0,2,0,23,1,8],[0],[3],[5]]]]
